r2x_pypsa/__init__.py
r2x_pypsa/exporter.py
r2x_pypsa/parser.py
r2x_pypsa/plugin.py
r2x_pypsa/sysmod.py
r2x_pypsa/models/__init__.py
r2x_pypsa/models/bus.py
r2x_pypsa/models/generator.py
r2x_pypsa/models/line.py
r2x_pypsa/models/link.py
r2x_pypsa/models/load.py
r2x_pypsa/models/property_values.py
r2x_pypsa/models/storage_unit.py
r2x_pypsa/models/store.py
r2x_pypsa/models/units.py
r2x_pypsa/serialization/__init__.py
r2x_pypsa/serialization/api.py
r2x_pypsa/serialization/cost_models.py
r2x_pypsa/serialization/pypsa_to_psy.py
r2x_pypsa/serialization/to_sienna.py
r2x_pypsa/serialization/utils.py
r2x_pypsa-0.1.1.dist-info/METADATA
r2x_pypsa-0.1.1.dist-info/WHEEL
r2x_pypsa-0.1.1.dist-info/licenses/LICENSE
r2x_pypsa-0.1.1.dist-info/RECORD
