Metadata-Version: 2.4
Name: r2x-pypsa
Version: 0.1.1
Summary: PyPSA to R2X parser and converter
Project-URL: Homepage, https://github.com/yourusername/r2x-pypsa
Project-URL: Repository, https://github.com/yourusername/r2x-pypsa
Project-URL: Documentation, https://github.com/yourusername/r2x-pypsa#readme
Project-URL: Bug Tracker, https://github.com/yourusername/r2x-pypsa/issues
Author-email: Kamran Tehranchi <ktehranchi@stanford.edu>, Henry Daniels-Koch <hdaniels@stanford.edu>
Maintainer-email: Kamran Tehranchi <ktehranchi@stanford.edu>, Henry Daniels-Koch <hdaniels@stanford.edu>
License: BSD 3-Clause License
License-File: LICENSE
Keywords: converter,parser,power-systems,pypsa,r2x,sienna
Classifier: Development Status :: 3 - Alpha
Classifier: Intended Audience :: Developers
Classifier: Intended Audience :: Science/Research
Classifier: License :: OSI Approved :: MIT License
Classifier: Operating System :: OS Independent
Classifier: Programming Language :: Python :: 3
Classifier: Programming Language :: Python :: 3.11
Classifier: Programming Language :: Python :: 3.12
Classifier: Topic :: Scientific/Engineering
Classifier: Topic :: Software Development :: Libraries :: Python Modules
Requires-Python: >=3.11
Requires-Dist: ipython>=9.6.0
Requires-Dist: loguru
Requires-Dist: pandas
Requires-Dist: pypsa==0.35.2
Requires-Dist: r2x>=1.1.0
Provides-Extra: dev
Requires-Dist: black; extra == 'dev'
Requires-Dist: flake8; extra == 'dev'
Requires-Dist: mypy; extra == 'dev'
Requires-Dist: pytest-cov; extra == 'dev'
Requires-Dist: pytest>=8.4.2; extra == 'dev'
Provides-Extra: test
Requires-Dist: pytest-cov; extra == 'test'
Requires-Dist: pytest>=8.4.2; extra == 'test'
